omnicontext/__init__.py
omnicontext/cli.py
omnicontext/schema.py
omnicontext/store.py
omnicontext/collectors/__init__.py
omnicontext/collectors/antigravity.py
omnicontext/collectors/base.py
omnicontext/collectors/chatgpt.py
omnicontext/collectors/claude.py
omnicontext/collectors/claude_code.py
omnicontext/collectors/cursor.py
omnicontext/collectors/gemini.py
omnicontext/collectors/grok.py
omnicontext/exporters/__init__.py
omnicontext/exporters/json.py
omnicontext/exporters/markdown.py
omnicontext/exporters/prompt.py
omnicontext-1.0.0.dist-info/METADATA
omnicontext-1.0.0.dist-info/WHEEL
omnicontext-1.0.0.dist-info/entry_points.txt
omnicontext-1.0.0.dist-info/top_level.txt
omnicontext-1.0.0.dist-info/RECORD
