Metadata-Version: 2.4
Name: omnicontext
Version: 1.0.0
Summary: Universal LLM context portability - take your AI conversations anywhere
Author: OmniContext Contributors
License: MIT
Classifier: Programming Language :: Python :: 3
Classifier: License :: OSI Approved :: MIT License
Classifier: Operating System :: OS Independent
Requires-Dist: click>=8.1.0
Requires-Dist: rich>=13.0.0
Requires-Dist: requests>=2.31.0
Requires-Dist: pydantic>=2.0.0
